excel_2_csv_converter/__init__.py
excel_2_csv_converter/excel_2_csv_converter.py
excel_2_csv_converter/setup.py
excel_2_csv_converter/test.py
excel_2_csv_converter-1.0.0.dist-info/METADATA
excel_2_csv_converter-1.0.0.dist-info/WHEEL
excel_2_csv_converter-1.0.0.dist-info/top_level.txt
excel_2_csv_converter-1.0.0.dist-info/RECORD
