Metadata-Version: 2.1
Name: excel-2-csv-converter
Version: 1.0.0
Summary: A package to convert Excel files to CSV
Home-page: https://github.com/yourusername/excel-converter
Author: Shambhu Jha
Author-email: shambhu.job1@gmail.com
License: UNKNOWN
Platform: UNKNOWN
Classifier: Development Status :: 5 - Production/Stable
Classifier: Intended Audience :: Developers
Classifier: License :: OSI Approved :: MIT License
Classifier: Programming Language :: Python :: 3
Classifier: Programming Language :: Python :: 3.6
Classifier: Programming Language :: Python :: 3.7
Classifier: Programming Language :: Python :: 3.8
Classifier: Programming Language :: Python :: 3.9
